rns_page_node/__init__.py
rns_page_node/cli.py
rns_page_node/config.py
rns_page_node/core.py
rns_page_node/handlers.py
rns_page_node/main.py
rns_page_node-1.4.0.dist-info/METADATA
rns_page_node-1.4.0.dist-info/WHEEL
rns_page_node-1.4.0.dist-info/entry_points.txt
rns_page_node-1.4.0.dist-info/licenses/LICENSE
rns_page_node-1.4.0.dist-info/RECORD
