Metadata-Version: 2.4
Name: rns-page-node
Version: 1.4.0
Summary: A simple way to serve pages and files over the Reticulum network.
License-Expression: GPL-3.0-only
License-File: LICENSE
Author: Sudo-Ivan
Requires-Python: >=3.9.2
Classifier: Programming Language :: Python :: 3
Classifier: Operating System :: OS Independent
Requires-Dist: cryptography (>=46.0.2)
Requires-Dist: rns (>=1.1.2,<1.5.0)
Project-URL: Homepage, https://git.quad4.io/RNS-Things/rns-page-node
Project-URL: Repository, https://git.quad4.io/RNS-Things/rns-page-node
